colorfulPyPrint/__init__.py
colorfulPyPrint/py_color.py
colorfulpyprint-0.2.0.dist-info/licenses/LICENSE
colorfulpyprint-0.2.0.dist-info/METADATA
colorfulpyprint-0.2.0.dist-info/WHEEL
colorfulpyprint-0.2.0.dist-info/top_level.txt
colorfulpyprint-0.2.0.dist-info/RECORD
