Metadata-Version: 2.4
Name: colorfulPyPrint
Version: 0.2.0
Summary: Utility for colored print and input statements
Home-page: https://github.com/roamingsaint/colorfulPyPrint.git
Author: Kanad Rishiraj (RoamingSaint)
Classifier: Programming Language :: Python :: 3
Classifier: License :: OSI Approved :: MIT License
Classifier: Operating System :: OS Independent
Requires-Python: >=3.9
License-File: LICENSE
Requires-Dist: termcolor
Requires-Dist: colorama
Dynamic: author
Dynamic: classifier
Dynamic: description
Dynamic: description-content-type
Dynamic: home-page
Dynamic: license-file
Dynamic: requires-dist
Dynamic: requires-python
Dynamic: summary
